{"created_at":"Sun May 27 14:46:13 +0000 2018","id":1000750023561433100,"id_str":"1000750023561433088","text":"@BraaainGOAT @SubsistCOD You know it’s game when a girl says she’s gonna fight you. \nGg subsist","display_text_range":[25,95],"source":"<a href=\"http://twitter.com/download/iphone\" rel=\"nofollow\">Twitter for iPhone</a>","truncated":false,"in_reply_to_status_id":1000501675470348300,"in_reply_to_status_id_str":"1000501675470348288","in_reply_to_user_id":2542087453,"in_reply_to_user_id_str":"2542087453","in_reply_to_screen_name":"BraaainGOAT","user":{"id":19564019,"id_str":"19564019","name":"Lisa Marie","screen_name":"xEmpressive","location":"NYC - LONDON","url":"http://twitch.tv/empressive","description":"25 | esports professional | Business Inquiries: lisanapolitano@yahoo.com","translator_type":"regular","protected":false,"verified":false,"followers_count":6070,"friends_count":707,"listed_count":62,"favourites_count":106323,"statuses_count":123079,"created_at":"Mon Jan 26 22:52:54 +0000 2009","utc_offset":null,"time_zone":null,"geo_enabled":false,"lang":"en","contributors_enabled":false,"is_translator":false,"profile_background_color":"000000","profile_background_image_url":"http://abs.twimg.com/images/themes/theme7/bg.gif","profile_background_image_url_https":"https://abs.twimg.com/images/themes/theme7/bg.gif","profile_background_tile":false,"profile_link_color":"F58EA8","profile_sidebar_border_color":"000000","profile_sidebar_fill_color":"000000","profile_text_color":"000000","profile_use_background_image":false,"profile_image_url":"http://pbs.twimg.com/profile_images/954967117429952512/TtlqA23b_normal.jpg","profile_image_url_https":"https://pbs.twimg.com/profile_images/954967117429952512/TtlqA23b_normal.jpg","profile_banner_url":"https://pbs.twimg.com/profile_banners/19564019/1511027804","default_profile":false,"default_profile_image":false,"following":null,"follow_request_sent":null,"notifications":null},"geo":null,"coordinates":null,"place":null,"contributors":null,"is_quote_status":false,"quote_count":0,"reply_count":0,"retweet_count":0,"favorite_count":0,"entities":{"hashtags":[],"urls":[],"user_mentions":[{"screen_name":"BraaainGOAT","name":"Brian","id":2542087453,"id_str":"2542087453","indices":[0,12]},{"screen_name":"SubsistCOD","name":"Laurens Schuurmans","id":2237539019,"id_str":"2237539019","indices":[13,24]}],"symbols":[]},"favorited":false,"retweeted":false,"filter_level":"low","lang":"en","timestamp_ms":"1527432373310"}